Workbook

Sheet dashboard
A1: BRAZIL TOMATO PRODUCTION ANALYSIS (2014–2023)
A2: AVERAGE PRODUCTION | B2: HIGHEST PRODUCTION | C2: LOWEST PRODUCTIONÇÃO | D2: TOTAL CHANGE (2014–2023)
A3: =analysis!F2 -> 4032382.9 | B3: =analysis!D2 -> 4302777 | C3: =analysis!E2 -> 3679256 | D3: =analysis!G2 -> -0.031784125
A7: KEY INSIGHTS
A8: 2021 | B8: ↑ 9,90% | C8: 2022 | D8: ↓ 8.3% | E8: 47,711 kg/ha
A9: Lowest production | B9: Growth in 2023 | C9: Recovery began | D9: Harvested area 2014–2023 | E9: Average state yield — 2023
H12: P

Sheet analysis
A1: ANO | B1: PRODUÇÃO DE TOMATE ( t) | C1: VARIAÇÃO ANUAL (%) | D1: MAIOR PRODUÇÃO | E1: MENOR PRODUÇÃO | F1: PRODUÇÃO MÉDIA | G1: VARIAÇÃO TOTAL 2014-2023 | H1: MAIOR CRESCIMENTO ANUAL | I1: MAIOR QUEDA ANUAL | J1: PRINCIPAIS INSIGHTS
A2: 2014 | B2: =SUM( 'Raw Data - Production'!C6:C33) -> 4302777 | D2: =(MAX(B2:B11)) -> 4302777 | E2: =MIN(B2:B11) -> 3679256 | F2: =AVERAGE(B2:B11) -> 4032382.9 | G2: =(B11-B2)/B2 -> -0.031784125 | H2: =MAX(C3:C11) -> 0.098985592 | I2: =MIN(C3:C11) -> -0.049913157 | J2: 1. Produção total caiu 3,18% entre 2014 e 2023
A3: 2015 | B3: =SUM('Raw Data - Production'!E6:E33) -> 4187729 | C3: =(B3-B2)/B2 -> -0.026738081 | D3: ANO DA MAIOR PRODUÇÃO | E3: ANO DA MENOR PRODUÇÃO | H3: ANO DO MAIOR CRESCIMENTO ANUAL | I3: ANO DA MAIOR QUEDA ANUAL | J3: 2. Menor produção ocorreu em 2021: 3679256 t.
A4: 2016 | B4: =SUM('Raw Data - Production'!G6:G33) -> 4166789 | C4: =(B4-B3)/B3 -> -0.0050003236 | D4: =INDEX(A2:A11,MATCH(D2,B2:B11,0)) -> 2014 | E4: =INDEX(A2:A11,MATCH(E2,B2:B11,0)) -> 2021 | H4: =INDEX(A3:A11,MATCH(H2,C3:C11,0)) -> 2023 | I4: =INDEX(A3:A11,MATCH(I2,C3:C11,0)) -> 2019 | J4: 3. Em 2023, a produção cresceu 9,9%, maior alta do período
A5: 2017 | B5: =SUM('Raw Data - Production'!I6:I33) -> 4225414 | C5: =(B5-B4)/B4 -> 0.014069587 | J5: 4. Apesar da recuperação de 2022-23, a produção permaneceu menor que a de 2014.
A6: 2018 | B6: =SUM('Raw Data - Production'!K6:K33) -> 4126988 | C6: =(B6-B5)/B5 -> -0.023293812
A7: 2019 | B7: =SUM('Raw Data - Production'!M6:M33) -> 3920997 | C7: =(B7-B6)/B6 -> -0.049913157
A8: 2020 | B8: =SUM( 'Raw Data - Production'!O6:O33) -> 3757078 | C8: =(B8-B7)/B7 -> -0.041805439
A9: 2021 | B9: =SUM('Raw Data - Production'!Q6:Q33) -> 3679256 | C9: =(B9-B8)/B8 -> -0.020713437
A10: 2022 | B10: =SUM('Raw Data - Production'!S6:S32) -> 3790784 | C10: =(B10-B9)/B9 -> 0.03031265
A11: 2023 | B11: =SUM('Raw Data - Production'!U6:U33) -> 4166017 | C11: =(B11-B10)/B10 -> 0.098985592

Sheet 2023 State Analysis
A3: STATE | B3: PRODUCTION 2023 (t)
A4: Acre | B4: -
A5: Amapá | B5: -
A6: Tocantins | B6: -
A7: Goiás | B7: 1242457
A8: São Paulo | B8: 867414
A9: Minas Gerais | B9: 561786
A10: Bahia | B10: 343195
A11: Paraná | B11: 228912
A12: Ceará | B12: 184799
A13: Espírito Santo | B13: 151594
A14: Santa Catarina | B14: 135597
A15: Rio de Janeiro | B15: 128118
A16: Pernambuco | B16: 120357
A17: Rio Grande do Sul | B17: 100112
A18: Distrito Federal | B18: 28000
A19: Paraíba | B19: 25638
A20: Alagoas | B20: 8523 | D20: KEY INSIGHTS
A21: Piauí | B21: 6598 | D21: 1. Goiás led national production: 1.24M tonnes.
A22: Rio Grande do Norte | B22: 6082 | D22: 2. São Paulo ranked second: 753K tonnes.
A23: Rondônia | B23: 5919 | D23: 3. Top 3 states accounted for ~54% of production.
A24: Sergipe | B24: 5460
A25: Pará | B25: 3788
A26: Maranhão | B26: 3772
A27: Mato Grosso | B27: 3511
A28: Roraima | B28: 2630
A29: Mato Grosso do Sul | B29: 1729
A30: Amazonas | B30: 26

Sheet Raw Data - Production
A1: Tabela 5457 - Área plantada ou destinada à colheita, área colhida, quantidade produzida, rendimento médio e valor da produção das lavouras temporárias e permanentes
A2: Variável - Quantidade produzida (Toneladas)
A3: Unidade da Federação | B3: Ano x Produto das lavouras temporárias e permanentes
B4: 2014 | D4: 2015 | F4: 2016 | H4: 2017 | J4: 2018 | L4: 2019 | N4: 2020 | P4: 2021 | R4: 2022 | T4: 2023
B5: Total | C5: Tomate | D5: Total | E5: Tomate | F5: Total | G5: Tomate | H5: Total | I5: Tomate | J5: Total | K5: Tomate | L5: Total | M5: Tomate | N5: Total | O5: Tomate | P5: Total | Q5: Tomate | R5: Total | S5: Tomate | T5: Total | U5: Tomate
A6: Rondônia | B6: .. | C6: 4986 | D6: .. | E6: 2542 | F6: .. | G6: 2766 | H6: .. | I6: 4868 | J6: .. | K6: 6289 | L6: .. | M6: 7437 | N6: .. | O6: 5324 | P6: .. | Q6: 4485 | R6: .. | S6: 6791 | T6: .. | U6: 5919
A7: Acre | B7: .. | C7: - | D7: .. | E7: - | F7: .. | G7: - | H7: .. | I7: - | J7: .. | K7: - | L7: .. | M7: - | N7: .. | O7: - | P7: .. | Q7: - | R7: .. | S7: - | T7: .. | U7: -
A8: Amazonas | B8: .. | C8: 601 | D8: .. | E8: 249 | F8: .. | G8: 162 | H8: .. | I8: 55 | J8: .. | K8: 200 | L8: .. | M8: 264 | N8: .. | O8: 300 | P8: .. | Q8: 281 | R8: .. | S8: 200 | T8: .. | U8: 26
A9: Roraima | B9: .. | C9: 3779 | D9: .. | E9: 4067 | F9: .. | G9: 4019 | H9: .. | I9: 1768 | J9: .. | K9: 1837 | L9: .. | M9: 2230 | N9: .. | O9: 2285 | P9: .. | Q9: 3222 | R9: .. | S9: 3135 | T9: .. | U9: 2630
A10: Pará | B10: .. | C10: 8700 | D10: .. | E10: 9315 | F10: .. | G10: 6580 | H10: .. | I10: 6240 | J10: .. | K10: 6197 | L10: .. | M10: 5610 | N10: .. | O10: 5679 | P10: .. | Q10: 5748 | R10: .. | S10: 4018 | T10: .. | U10: 3788
A11: Amapá | B11: .. | C11: - | D11: .. | E11: - | F11: .. | G11: - | H11: .. | I11: - | J11: .. | K11: - | L11: .. | M11: - | N11: .. | O11: - | P11: .. | Q11: - | R11: .. | S11: - | T11: .. | U11: -
A12: Tocantins | B12: .. | C12: - | D12: .. | E12: - | F12: .. | G12: - | H12: .. | I12: - | J12: .. | K12: - | L12: .. | M12: - | N12: .. | O12: - | P12: .. | Q12: - | R12: .. | S12: - | T12: .. | U12: -
A13: Maranhão | B13: .. | C13: 4199 | D13: .. | E13: 4330 | F13: .. | G13: 3671 | H13: .. | I13: 4005 | J13: .. | K13: 4730 | L13: .. | M13: 4533 | N13: .. | O13: 3703 | P13: .. | Q13: 3288 | R13: .. | S13: 3125 | T13: .. | U13: 3772
A14: Piauí | B14: .. | C14: 3320 | D14: .. | E14: 3120 | F14: .. | G14: 2498 | H14: .. | I14: 3150 | J14: .. | K14: 5136 | L14: .. | M14: 4511 | N14: .. | O14: 5319 | P14: .. | Q14: 4095 | R14: .. | S14: 4343 | T14: .. | U14: 6598
A15: Ceará | B15: .. | C15: 113724 | D15: .. | E15: 95128 | F15: .. | G15: 122846 | H15: .. | I15: 120397 | J15: .. | K15: 134932 | L15: .. | M15: 157060 | N15: .. | O15: 177575 | P15: .. | Q15: 166889 | R15: .. | S15: 170059 | T15: .. | U15: 184799
A16: Rio Grande do Norte | B16: .. | C16: 6606 | D16: .. | E16: 3828 | F16: .. | G16: 4696 | H16: .. | I16: 3768 | J16: .. | K16: 5274 | L16: .. | M16: 7117 | N16: .. | O16: 6157 | P16: .. | Q16: 5115 | R16: .. | S16: 6090 | T16: .. | U16: 6082
A17: Paraíba | B17: .. | C17: 14155 | D17: .. | E17: 13045 | F17: .. | G17: 8955 | H17: .. | I17: 10536 | J17: .. | K17: 17898 | L17: .. | M17: 13707 | N17: .. | O17: 13419 | P17: .. | Q17: 17298 | R17: .. | S17: 18897 | T17: .. | U17: 25638
A18: Pernambuco | B18: .. | C18: 128881 | D18: .. | E18: 93718 | F18: .. | G18: 53331 | H18: .. | I18: 60430 | J18: .. | K18: 61478 | L18: .. | M18: 64406 | N18: .. | O18: 57393 | P18: .. | Q18: 67128 | R18: .. | S18: 67154 | T18: .. | U18: 120357
A19: Alagoas | B19: .. | C19: 5032 | D19: .. | E19: 5380 | F19: .. | G19: 6168 | H19: .. | I19: 6641 | J19: .. | K19: 7543 | L19: .. | M19: 8720 | N19: .. | O19: 7799 | P19: .. | Q19: 8990 | R19: .. | S19: 9501 | T19: .. | U19: 8523
A20: Sergipe | B20: .. | C20: 1633 | D20: .. | E20: 1274 | F20: .. | G20: 357 | H20: .. | I20: - | J20: .. | K20: 1395 | L20: .. | M20: 3620 | N20: .. | O20: 5060 | P20: .. | Q20: 7530 | R20: .. | S20: 8660 | T20: .. | U20: 5460
A21: Bahia | B21: .. | C21: 288477 | D21: .. | E21: 323660 | F21: .. | G21: 335044 | H21: .. | I21: 286936 | J21: .. | K21: 260918 | L21: .. | M21: 235836 | N21: .. | O21: 228267 | P21: .. | Q21: 261404 | R21: .. | S21: 274490 | T21: .. | U21: 343195
A22: Minas Gerais | B22: .. | C22: 674962 | D22: .. | E22: 715890 | F22: .. | G22: 702510 | H22: .. | I22: 572273 | J22: .. | K22: 539583 | L22: .. | M22: 526309 | N22: .. | O22: 513906 | P22: .. | Q22: 553429 | R22: .. | S22: 578116 | T22: .. | U22: 561786
A23: Espírito Santo | B23: .. | C23: 188420 | D23: .. | E23: 144834 | F23: .. | G23: 152024 | H23: .. | I23: 164781 | J23: .. | K23: 173145 | L23: .. | M23: 163943 | N23: .. | O23: 151590 | P23: .. | Q23: 147537 | R23: .. | S23: 151636 | T23: .. | U23: 151594
A24: Rio de Janeiro | B24: .. | C24: 207424 | D24: .. | E24: 185889 | F24: .. | G24: 179205 | H24: .. | I24: 175751 | J24: .. | K24: 154272 | L24: .. | M24: 141195 | N24: .. | O24: 155890 | P24: .. | Q24: 156917 | R24: .. | S24: 144818 | T24: .. | U24: 128118
A25: Guanabara | B25: .. | C25: ... | D25: .. | E25: ... | F25: .. | G25: ... | H25: .. | I25: ... | J25: .. | K25: ... | L25: .. | M25: ... | N25: .. | O25: ... | P25: .. | Q25: ... | R25: .. | S25: ... | T25: .. | U25: ...
A26: São Paulo | B26: .. | C26: 956869 | D26: .. | E26: 1097937 | F26: .. | G26: 1101336 | H26: .. | I26: 929793 | J26: .. | K26: 870598 | L26: .. | M26: 918497 | N26: .. | O26: 801471 | P26: .. | Q26: 742395 | R26: .. | S26: 917349 | T26: .. | U26: 867414
A27: Paraná | B27: .. | C27: 253362 | D27: .. | E27: 230319 | F27: .. | G27: 217430 | H27: .. | I27: 251607 | J27: .. | K27: 237133 | L27: .. | M27: 230611 | N27: .. | O27: 225004 | P27: .. | Q27: 211165 | R27: .. | S27: 214465 | T27: .. | U27: 228912
A28: Santa Catarina | B28: .. | C28: 184482 | D28: .. | E28: 180486 | F28: .. | G28: 172275 | H28: .. | I28: 173167 | J28: .. | K28: 175710 | L28: .. | M28: 161948 | N28: .. | O28: 168975 | P28: .. | Q28: 158286 | R28: .. | S28: 118700 | T28: .. | U28: 135597
A29: Rio Grande do Sul | B29: .. | C29: 117176 | D29: .. | E29: 111363 | F29: .. | G29: 112363 | H29: .. | I29: 116742 | J29: .. | K29: 98574 | L29: .. | M29: 104141 | N29: .. | O29: 89934 | P29: .. | Q29: 94967 | R29: .. | S29: 90675 | T29: .. | U29: 100112
A30: Mato Grosso do Sul | B30: .. | C30: 2791 | D30: .. | E30: 2420 | F30: .. | G30: 2705 | H30: .. | I30: 2720 | J30: .. | K30: 2425 | L30: .. | M30: 1582 | N30: .. | O30: 2041 | P30: .. | Q30: 1350 | R30: .. | S30: 1537 | T30: .. | U30: 1729
A31: Mato Grosso | B31: .. | C31: 9426 | D31: .. | E31: 9268 | F31: .. | G31: 9637 | H31: .. | I31: 5498 | J31: .. | K31: 3931 | L31: .. | M31: 3625 | N31: .. | O31: 3676 | P31: .. | Q31: 3682 | R31: .. | S31: 3573 | T31: .. | U31: 3511
A32: Goiás | B32: .. | C32: 1055337 | D32: .. | E32: 912976 | F32: .. | G32: 934658 | H32: .. | I32: 1298088 | J32: .. | K32: 1329790 | L32: .. | M32: 1126095 | N32: .. | O32: 1098311 | P32: .. | Q32: 1026055 | R32: .. | S32: 993452 | T32: .. | U32: 1242457
A33: Distrito Federal | B33: .. | C33: 68435 | D33: .. | E33: 36691 | F33: .. | G33: 31553 | H33: .. | I33: 26200 | J33: .. | K33: 28000 | L33: .. | M33: 28000 | N33: .. | O33: 28000 | P33: .. | Q33: 28000 | R33: .. | S33: 28000 | T33: .. | U33: 28000
A34: Fonte: IBGE - Produção Agrícola Municipal

Sheet Raw Data - Harvested Area
A1: Tabela 5457 - Área plantada ou destinada à colheita, área colhida, quantidade produzida, rendimento médio e valor da produção das lavouras temporárias e permanentes
A2: Variável - Área colhida (Hectares)
A3: Unidade da Federação | B3: Ano x Produto das lavouras temporárias e permanentes
B4: 2014 | D4: 2015 | F4: 2016 | H4: 2017 | J4: 2018 | L4: 2019 | N4: 2020 | P4: 2021 | R4: 2022 | T4: 2023
B5: Total | C5: Tomate | D5: Total | E5: Tomate | F5: Total | G5: Tomate | H5: Total | I5: Tomate | J5: Total | K5: Tomate | L5: Total | M5: Tomate | N5: Total | O5: Tomate | P5: Total | Q5: Tomate | R5: Total | S5: Tomate | T5: Total | U5: Tomate
A6: Rondônia | B6: 573067 | C6: 267 | D6: 611967 | E6: 154 | F6: 608004 | G6: 180 | H6: 683098 | I6: 138 | J6: 656737 | K6: 201 | L6: 740035 | M6: 240 | N6: 805371 | O6: 160 | P6: 849127 | Q6: 157 | R6: 961705 | S6: 212 | T6: 1080130 | U6: 174
A7: Acre | B7: 117668 | C7: - | D7: 107599 | E7: - | F7: 106538 | G7: - | H7: 97553 | I7: - | J7: 82836 | K7: - | L7: 79177 | M7: - | N7: 79458 | O7: - | P7: 84133 | Q7: - | R7: 89950 | S7: - | T7: 95060 | U7: -
A8: Amazonas | B8: 125850 | C8: 42 | D8: 118257 | E8: 20 | F8: 119475 | G8: 13 | H8: 128292 | I8: 6 | J8: 120557 | K8: 22 | L8: 117817 | M8: 30 | N8: 119128 | O8: 34 | P8: 112934 | Q8: 33 | R8: 118008 | S8: 24 | T8: 114401 | U8: 4
A9: Roraima | B9: 59223 | C9: 296 | D9: 65113 | E9: 250 | F9: 61462 | G9: 246 | H9: 57352 | I9: 121 | J9: 75815 | K9: 118 | L9: 81597 | M9: 130 | N9: 94052 | O9: 120 | P9: 123264 | Q9: 162 | R9: 150608 | S9: 150 | T9: 175947 | U9: 131
A10: Pará | B10: 1249770 | C10: 347 | D10: 1468661 | E10: 360 | F10: 1565725 | G10: 254 | H10: 1725643 | I10: 242 | J10: 1698250 | K10: 233 | L10: 1806069 | M10: 208 | N10: 2010218 | O10: 210 | P10: 2158669 | Q10: 212 | R10: 2311915 | S10: 167 | T10: 2543535 | U10: 158
A11: Amapá | B11: 41258 | C11: - | D11: 33704 | E11: - | F11: 36232 | G11: - | H11: 41630 | I11: - | J11: 35761 | K11: - | L11: 36306 | M11: - | N11: 38242 | O11: - | P11: 28113 | Q11: - | R11: 27184 | S11: - | T11: 24631 | U11: -
A12: Tocantins | B12: 1037140 | C12: - | D12: 1203553 | E12: - | F12: 1200125 | G12: - | H12: 1282462 | I12: - | J12: 1361419 | K12: - | L12: 1426906 | M12: - | N12: 1544660 | O12: - | P12: 1734385 | Q12: - | R12: 1873313 | S12: - | T12: 2151789 | U12: -
A13: Maranhão | B13: 2005779 | C13: 210 | D13: 1829354 | E13: 217 | F13: 1584338 | G13: 189 | H13: 1803687 | I13: 197 | J13: 1819981 | K13: 220 | L13: 1721828 | M13: 222 | N13: 1719030 | O13: 184 | P13: 1810779 | Q13: 170 | R13: 1920950 | S13: 154 | T13: 2015293 | U13: 168
A14: Piauí | B14: 1491554 | C14: 161 | D14: 1480523 | E14: 141 | F14: 1343593 | G14: 132 | H14: 1594307 | I14: 141 | J14: 1608186 | K14: 176 | L14: 1618462 | M14: 157 | N14: 1654236 | O14: 158 | P14: 1739147 | Q14: 186 | R14: 1882048 | S14: 175 | T14: 1973449 | U14: 204
A15: Ceará | B15: 1503104 | C15: 2230 | D15: 1492991 | E15: 2198 | F15: 1435573 | G15: 2532 | H15: 1521661 | I15: 2575 | J15: 1469310 | K15: 2398 | L15: 1365496 | M15: 2436 | N15: 1384688 | O15: 2498 | P15: 1408091 | Q15: 2332 | R15: 1440333 | S15: 2335 | T15: 1452932 | U15: 2550
A16: Rio Grande do Norte | B16: 288548 | C16: 230 | D16: 228991 | E16: 123 | F16: 204136 | G16: 148 | H16: 238073 | I16: 137 | J16: 300196 | K16: 180 | L16: 315424 | M16: 245 | N16: 317266 | O16: 197 | P16: 262580 | Q16: 171 | R16: 303246 | S16: 194 | T16: 306885 | U16: 202
A17: Paraíba | B17: 330585 | C17: 403 | D17: 287805 | E17: 439 | F17: 332362 | G17: 287 | H17: 319900 | I17: 380 | J17: 361742 | K17: 605 | L17: 330461 | M17: 479 | N17: 369045 | O17: 454 | P17: 308712 | Q17: 575 | R17: 346881 | S17: 625 | T17: 344634 | U17: 861
A18: Pernambuco | B18: 782413 | C18: 3731 | D18: 614679 | E18: 2527 | F18: 584297 | G18: 1602 | H18: 623815 | I18: 1501 | J18: 680757 | K18: 1287 | L18: 592422 | M18: 1541 | N18: 720780 | O18: 1442 | P18: 667445 | Q18: 1373 | R18: 694196 | S18: 1460 | T18: 630478 | U18: 2211
A19: Alagoas | B19: 540405 | C19: 68 | D19: 428604 | E19: 72 | F19: 404493 | G19: 111 | H19: 481571 | I19: 105 | J19: 409887 | K19: 124 | L19: 461101 | M19: 158 | N19: 442350 | O19: 139 | P19: 468136 | Q19: 147 | R19: 424033 | S19: 213 | T19: 439948 | U19: 190
A20: Sergipe | B20: 359618 | C20: 98 | D20: 343090 | E20: 76 | F20: 262675 | G20: 22 | H20: 334945 | I20: - | J20: 159459 | K20: 42 | L20: 262702 | M20: 120 | N20: 275690 | O20: 148 | P20: 286925 | Q20: 251 | R20: 297674 | S20: 260 | T20: 304631 | U20: 160
A21: Bahia | B21: 4579150 | C21: 6447 | D21: 4846152 | E21: 7103 | F21: 4315806 | G21: 7096 | H21: 3824862 | I21: 5056 | J21: 3977002 | K21: 4643 | L21: 4012783 | M21: 4415 | N21: 4094295 | O21: 4223 | P21: 4146367 | Q21: 4784 | R21: 4340110 | S21: 5042 | T21: 4522809 | U21: 6126
A22: Minas Gerais | B22: 5368786 | C22: 9293 | D22: 5334772 | E22: 9758 | F22: 5373130 | G22: 10303 | H22: 5240285 | I22: 7556 | J22: 5311185 | K22: 7320 | L22: 5560336 | M22: 7039 | N22: 5800675 | O22: 6871 | P22: 5944278 | Q22: 7336 | R22: 6249522 | S22: 7720 | T22: 6679784 | U22: 7485
A23: Espírito Santo | B23: 657624 | C23: 2605 | D23: 644523 | E23: 2503 | F23: 613805 | G23: 2510 | H23: 584247 | I23: 2532 | J23: 558885 | K23: 2629 | L23: 558258 | M23: 2583 | N23: 565046 | O23: 2618 | P23: 578947 | Q23: 2503 | R23: 599778 | S23: 2364 | T23: 609499 | U23: 2352
A24: Rio de Janeiro | B24: 170600 | C24: 2714 | D24: 148284 | E24: 2529 | F24: 123939 | G24: 2444 | H24: 113891 | I24: 2550 | J24: 109210 | K24: 2325 | L24: 113309 | M24: 2132 | N24: 112252 | O24: 2268 | P24: 115790 | Q24: 2310 | R24: 113487 | S24: 2179 | T24: 105268 | U24: 1953
A25: Guanabara | B25: ... | C25: ... | D25: ... | E25: ... | F25: ... | G25: ... | H25: ... | I25: ... | J25: ... | K25: ... | L25: ... | M25: ... | N25: ... | O25: ... | P25: ... | Q25: ... | R25: ... | S25: ... | T25: ... | U25: ...
A26: São Paulo | B26: 8320378 | C26: 12685 | D26: 8425060 | E26: 14965 | F26: 8624268 | G26: 14819 | H26: 8820082 | I26: 12108 | J26: 8650001 | K26: 11075 | L26: 8842804 | M26: 11195 | N26: 8857885 | O26: 10090 | P26: 8795581 | Q26: 9815 | R26: 9056594 | S26: 11525 | T26: 9198986 | U26: 11475
A27: Paraná | B27: 10704717 | C27: 4396 | D27: 10619322 | E27: 3746 | F27: 10704291 | G27: 3836 | H27: 10614860 | I27: 4154 | J27: 10451016 | K27: 3994 | L27: 10639983 | M27: 3800 | N27: 10865644 | O27: 3642 | P27: 10988227 | Q27: 3593 | R27: 11489689 | S27: 3403 | T27: 11464429 | U27: 3612
A28: Santa Catarina | B28: 1615086 | C28: 2735 | D28: 1581244 | E28: 2644 | F28: 1573363 | G28: 2769 | H28: 1548103 | I28: 2699 | J28: 1512716 | K28: 2555 | L28: 1505000 | M28: 2462 | N28: 1509824 | O28: 2518 | P28: 1569221 | Q28: 2507 | R28: 1668620 | S28: 1976 | T28: 1667894 | U28: 1993
A29: Rio Grande do Sul | B29: 9031185 | C29: 2373 | D29: 8941887 | E29: 2269 | F29: 8869923 | G29: 2317 | H29: 9055832 | I29: 2277 | J29: 8995602 | K29: 1954 | L29: 9170906 | M29: 2120 | N29: 9500873 | O29: 2090 | P29: 9954418 | Q29: 2041 | R29: 10355832 | S29: 1964 | T29: 10664286 | U29: 1940
A30: Mato Grosso do Sul | B30: 4555459 | C30: 69 | D30: 4743631 | E30: 69 | F30: 4899405 | G30: 77 | H30: 5282706 | I30: 66 | J30: 5467545 | K30: 71 | L30: 5791872 | M30: 47 | N30: 5956336 | O30: 47 | P30: 6175166 | Q30: 40 | R30: 6925653 | S30: 49 | T30: 7276371 | U30: 51
A31: Mato Grosso | B31: 13552610 | C31: 232 | D31: 14112886 | E31: 227 | F31: 14297088 | G31: 243 | H31: 15586181 | I31: 227 | J31: 15515876 | K31: 184 | L31: 16632047 | M31: 169 | N31: 17187508 | O31: 177 | P31: 17954671 | Q31: 183 | R31: 19158124 | S31: 176 | T31: 21256358 | U31: 171
A32: Goiás | B32: 6135201 | C32: 11720 | D32: 6114291 | E32: 10653 | F32: 6049297 | G32: 11452 | H32: 6431544 | I32: 16307 | J32: 6344144 | K32: 14682 | L32: 6663002 | M32: 12313 | N32: 6929925 | O32: 11368 | P32: 7327842 | Q32: 10677 | R32: 7638596 | S32: 11624 | T32: 8454151 | U32: 14489
A33: Distrito Federal | B33: 175023 | C33: 1011 | D33: 160622 | E33: 529 | F33: 166419 | G33: 413 | H33: 162894 | I33: 328 | J33: 164900 | K33: 350 | L33: 163915 | M33: 350 | N33: 171535 | O33: 350 | P33: 166835 | Q33: 350 | R33: 173925 | S33: 350 | T33: 175965 | U33: 350
A34: Fonte: IBGE - Produção Agrícola Municipal

Sheet Raw Data - Yield
A1: Tabela 5457 - Área plantada ou destinada à colheita, área colhida, quantidade produzida, rendimento médio e valor da produção das lavouras temporárias e permanentes
A2: Variável - Rendimento médio da produção (Quilogramas por Hectare)
A3: Unidade da Federação | B3: Ano x Produto das lavouras temporárias e permanentes
B4: 2014 | D4: 2015 | F4: 2016 | H4: 2017 | J4: 2018 | L4: 2019 | N4: 2020 | P4: 2021 | R4: 2022 | T4: 2023
B5: Total | C5: Tomate | D5: Total | E5: Tomate | F5: Total | G5: Tomate | H5: Total | I5: Tomate | J5: Total | K5: Tomate | L5: Total | M5: Tomate | N5: Total | O5: Tomate | P5: Total | Q5: Tomate | R5: Total | S5: Tomate | T5: Total | U5: Tomate
A6: Rondônia | B6: .. | C6: 18674 | D6: .. | E6: 16506 | F6: .. | G6: 15367 | H6: .. | I6: 35275 | J6: .. | K6: 31289 | L6: .. | M6: 30988 | N6: .. | O6: 33275 | P6: .. | Q6: 28567 | R6: .. | S6: 32033 | T6: .. | U6: 34017
A7: Acre | B7: .. | C7: - | D7: .. | E7: - | F7: .. | G7: - | H7: .. | I7: - | J7: .. | K7: - | L7: .. | M7: - | N7: .. | O7: - | P7: .. | Q7: - | R7: .. | S7: - | T7: .. | U7: -
A8: Amazonas | B8: .. | C8: 14310 | D8: .. | E8: 12450 | F8: .. | G8: 12462 | H8: .. | I8: 9167 | J8: .. | K8: 9091 | L8: .. | M8: 8800 | N8: .. | O8: 8824 | P8: .. | Q8: 8515 | R8: .. | S8: 8333 | T8: .. | U8: 6500
A9: Roraima | B9: .. | C9: 12767 | D9: .. | E9: 16268 | F9: .. | G9: 16337 | H9: .. | I9: 14612 | J9: .. | K9: 15568 | L9: .. | M9: 17154 | N9: .. | O9: 19042 | P9: .. | Q9: 19889 | R9: .. | S9: 20900 | T9: .. | U9: 20076
A10: Pará | B10: .. | C10: 25072 | D10: .. | E10: 25875 | F10: .. | G10: 25906 | H10: .. | I10: 25785 | J10: .. | K10: 26597 | L10: .. | M10: 26971 | N10: .. | O10: 27043 | P10: .. | Q10: 27113 | R10: .. | S10: 24060 | T10: .. | U10: 23975
A11: Amapá | B11: .. | C11: - | D11: .. | E11: - | F11: .. | G11: - | H11: .. | I11: - | J11: .. | K11: - | L11: .. | M11: - | N11: .. | O11: - | P11: .. | Q11: - | R11: .. | S11: - | T11: .. | U11: -
A12: Tocantins | B12: .. | C12: - | D12: .. | E12: - | F12: .. | G12: - | H12: .. | I12: - | J12: .. | K12: - | L12: .. | M12: - | N12: .. | O12: - | P12: .. | Q12: - | R12: .. | S12: - | T12: .. | U12: -
A13: Maranhão | B13: .. | C13: 19995 | D13: .. | E13: 19954 | F13: .. | G13: 19423 | H13: .. | I13: 20330 | J13: .. | K13: 21500 | L13: .. | M13: 20419 | N13: .. | O13: 20125 | P13: .. | Q13: 19341 | R13: .. | S13: 20292 | T13: .. | U13: 22452
A14: Piauí | B14: .. | C14: 20621 | D14: .. | E14: 22128 | F14: .. | G14: 18924 | H14: .. | I14: 22340 | J14: .. | K14: 29182 | L14: .. | M14: 28732 | N14: .. | O14: 33665 | P14: .. | Q14: 22016 | R14: .. | S14: 24817 | T14: .. | U14: 32343
A15: Ceará | B15: .. | C15: 50997 | D15: .. | E15: 43279 | F15: .. | G15: 48517 | H15: .. | I15: 46756 | J15: .. | K15: 56269 | L15: .. | M15: 64475 | N15: .. | O15: 71087 | P15: .. | Q15: 71565 | R15: .. | S15: 72830 | T15: .. | U15: 72470
A16: Rio Grande do Norte | B16: .. | C16: 28722 | D16: .. | E16: 31122 | F16: .. | G16: 31730 | H16: .. | I16: 27504 | J16: .. | K16: 29300 | L16: .. | M16: 29049 | N16: .. | O16: 31254 | P16: .. | Q16: 29912 | R16: .. | S16: 31392 | T16: .. | U16: 30109
A17: Paraíba | B17: .. | C17: 35124 | D17: .. | E17: 29715 | F17: .. | G17: 31202 | H17: .. | I17: 27726 | J17: .. | K17: 29583 | L17: .. | M17: 28616 | N17: .. | O17: 29557 | P17: .. | Q17: 30083 | R17: .. | S17: 30235 | T17: .. | U17: 29777
A18: Pernambuco | B18: .. | C18: 34543 | D18: .. | E18: 37087 | F18: .. | G18: 33290 | H18: .. | I18: 40260 | J18: .. | K18: 47768 | L18: .. | M18: 41795 | N18: .. | O18: 39801 | P18: .. | Q18: 48891 | R18: .. | S18: 45996 | T18: .. | U18: 54436
A19: Alagoas | B19: .. | C19: 74000 | D19: .. | E19: 74722 | F19: .. | G19: 55568 | H19: .. | I19: 63248 | J19: .. | K19: 60831 | L19: .. | M19: 55190 | N19: .. | O19: 56108 | P19: .. | Q19: 61156 | R19: .. | S19: 44606 | T19: .. | U19: 44858
A20: Sergipe | B20: .. | C20: 16663 | D20: .. | E20: 16763 | F20: .. | G20: 16227 | H20: .. | I20: - | J20: .. | K20: 33214 | L20: .. | M20: 30167 | N20: .. | O20: 34189 | P20: .. | Q20: 30000 | R20: .. | S20: 33308 | T20: .. | U20: 34125
A21: Bahia | B21: .. | C21: 44746 | D21: .. | E21: 45567 | F21: .. | G21: 47216 | H21: .. | I21: 56752 | J21: .. | K21: 56196 | L21: .. | M21: 53417 | N21: .. | O21: 54053 | P21: .. | Q21: 54641 | R21: .. | S21: 54441 | T21: .. | U21: 56023
A22: Minas Gerais | B22: .. | C22: 72631 | D22: .. | E22: 73364 | F22: .. | G22: 68185 | H22: .. | I22: 75738 | J22: .. | K22: 73714 | L22: .. | M22: 74770 | N22: .. | O22: 74793 | P22: .. | Q22: 75440 | R22: .. | S22: 74885 | T22: .. | U22: 75055
A23: Espírito Santo | B23: .. | C23: 72330 | D23: .. | E23: 57864 | F23: .. | G23: 60567 | H23: .. | I23: 65079 | J23: .. | K23: 65860 | L23: .. | M23: 63470 | N23: .. | O23: 57903 | P23: .. | Q23: 58944 | R23: .. | S23: 64144 | T23: .. | U23: 64453
A24: Rio de Janeiro | B24: .. | C24: 76427 | D24: .. | E24: 73503 | F24: .. | G24: 73324 | H24: .. | I24: 68922 | J24: .. | K24: 66354 | L24: .. | M24: 66227 | N24: .. | O24: 68735 | P24: .. | Q24: 67929 | R24: .. | S24: 66461 | T24: .. | U24: 65601
A25: Guanabara | B25: .. | C25: ... | D25: .. | E25: ... | F25: .. | G25: ... | H25: .. | I25: ... | J25: .. | K25: ... | L25: .. | M25: ... | N25: .. | O25: ... | P25: .. | Q25: ... | R25: .. | S25: ... | T25: .. | U25: ...
A26: São Paulo | B26: .. | C26: 75433 | D26: .. | E26: 73367 | F26: .. | G26: 74319 | H26: .. | I26: 76792 | J26: .. | K26: 78609 | L26: .. | M26: 82045 | N26: .. | O26: 79432 | P26: .. | Q26: 75639 | R26: .. | S26: 79596 | T26: .. | U26: 75592
A27: Paraná | B27: .. | C27: 57635 | D27: .. | E27: 61484 | F27: .. | G27: 56681 | H27: .. | I27: 60570 | J27: .. | K27: 59372 | L27: .. | M27: 60687 | N27: .. | O27: 61780 | P27: .. | Q27: 58771 | R27: .. | S27: 63022 | T27: .. | U27: 63375
A28: Santa Catarina | B28: .. | C28: 67452 | D28: .. | E28: 68262 | F28: .. | G28: 62216 | H28: .. | I28: 64160 | J28: .. | K28: 68771 | L28: .. | M28: 65779 | N28: .. | O28: 67107 | P28: .. | Q28: 63138 | R28: .. | S28: 60071 | T28: .. | U28: 68037
A29: Rio Grande do Sul | B29: .. | C29: 49379 | D29: .. | E29: 49080 | F29: .. | G29: 48495 | H29: .. | I29: 51270 | J29: .. | K29: 50447 | L29: .. | M29: 49123 | N29: .. | O29: 43031 | P29: .. | Q29: 46530 | R29: .. | S29: 46169 | T29: .. | U29: 51604
A30: Mato Grosso do Sul | B30: .. | C30: 40449 | D30: .. | E30: 35072 | F30: .. | G30: 35130 | H30: .. | I30: 41212 | J30: .. | K30: 34155 | L30: .. | M30: 33660 | N30: .. | O30: 43426 | P30: .. | Q30: 33750 | R30: .. | S30: 31367 | T30: .. | U30: 33902
A31: Mato Grosso | B31: .. | C31: 40629 | D31: .. | E31: 40828 | F31: .. | G31: 39658 | H31: .. | I31: 24220 | J31: .. | K31: 21364 | L31: .. | M31: 21450 | N31: .. | O31: 20768 | P31: .. | Q31: 20120 | R31: .. | S31: 20301 | T31: .. | U31: 20532
A32: Goiás | B32: .. | C32: 90046 | D32: .. | E32: 85701 | F32: .. | G32: 81615 | H32: .. | I32: 79603 | J32: .. | K32: 90573 | L32: .. | M32: 91456 | N32: .. | O32: 96614 | P32: .. | Q32: 96100 | R32: .. | S32: 85466 | T32: .. | U32: 85752
A33: Distrito Federal | B33: .. | C33: 67690 | D33: .. | E33: 69359 | F33: .. | G33: 76400 | H33: .. | I33: 79878 | J33: .. | K33: 80000 | L33: .. | M33: 80000 | N33: .. | O33: 80000 | P33: .. | Q33: 80000 | R33: .. | S33: 80000 | T33: .. | U33: 80000
A34: Fonte: IBGE - Produção Agrícola Municipal

Sheet Harvested Area Analysis
A1: YEAR | B1: HARVESTED AREA (ha) | C1: =(B11-B2)/B2 -> -0.083168901
A2: 2014 | B2: =SUM('Raw Data - Harvested Area'!C6:C33) -> 64363 | C2: insights
A3: 2015 | B3: =SUM('Raw Data - Harvested Area'!E6:E33) -> 63572 | C3: Harvested area decreased by 8,3 % from 2014 to 2023.
A4: 2016 | B4: =SUM('Raw Data - Harvested Area'!G6:G33) -> 63995 | C4: Harvested area reached its lowest level in 2021.
A5: 2017 | B5: =SUM('Raw Data - Harvested Area'!I6:I33) -> 61403
A6: 2018 | B6: =SUM('Raw Data - Harvested Area'!K6:K33) -> 57388
A7: 2019 | B7: =SUM('Raw Data - Harvested Area'!M6:M33) -> 54591
A8: 2020 | B8: =SUM('Raw Data - Harvested Area'!O6:O33) -> 52006
A9: 2021 | B9: =SUM('Raw Data - Harvested Area'!Q6:Q33) -> 51908
A10: 2022 | B10: =SUM('Raw Data - Harvested Area'!S6:S33) -> 54341
A11: 2023 | B11: =SUM('Raw Data - Harvested Area'!U6:U33) -> 59010

Sheet yield analysis
A1: STATE | B1: YIELD 2023 (kg/ha) | C1: AVERAGE YIELD 2023
A2: Acre | B2: -
A3: Amapá | B3: - | C3: =AVERAGE(B5:B28) -> 47711
A4: Tocantins | B4: -
A5: Goiás | B5: 85752 | C5: INSIGHT
A6: Distrito Federal | B6: 80000 | C6: Average state yiel: 47711kg/ ha
A7: São Paulo | B7: 75592 | C7: Goiás had the highest tomato yield in 2023: 85,752 kg/ha.
A8: Minas Gerais | B8: 75055 | C8: The top 5 states achieved yields above 72,000 kg/ha.
A9: Ceará | B9: 72470
A10: Santa Catarina | B10: 68037
A11: Rio de Janeiro | B11: 65601
A12: Espírito Santo | B12: 64453
A13: Paraná | B13: 63375
A14: Bahia | B14: 56023
A15: Pernambuco | B15: 54436
A16: Rio Grande do Sul | B16: 51604
A17: Alagoas | B17: 44858
A18: Sergipe | B18: 34125
A19: Rondônia | B19: 34017
A20: Mato Grosso do Sul | B20: 33902
... A28: Amazonas | B28: 6500

Sheet notes
A1: Notas
A2: 1 - Os municípios sem informação para pelo menos um produto da lavoura não aparecem nas listas;
A3: 2 - A partir do ano de 2001 as quantidades produzidas dos produtos abacate, banana, caqui, figo, goiaba, laranja, limão, maçã, mamão, manga, maracujá, marmelo, melancia, melão, pera, pêssego e tangerina passam a ser expressas em toneladas. Nos anos anteriores eram expressas em mil frutos, com exceção da banana, que era expressa em mil cachos. O rendimento médio passa a ser expresso em Kg/ha. Nos anos anteriores era expresso em frutos/ha, com exceção da banana, que era expressa em cachos/ha.
A4: 3 - Veja em https://sidra.ibge.gov.br/content/documentos/pam/AlteracoesUnidadesMedidaFrutas.pdf um documento com as alterações de unidades de medida das frutíferas ocorridas em 2001 e a tabela de conversão fruto x quilograma.
A5: 4 - Até 2001, café (em coco), a partir de 2002, café (beneficiado ou em grão).
A6: 5 - Os produtos girassol e triticale só apresentam informação a partir de 2005.
A7: 6 - As quantidades produzidas de abacaxi e de coco-da-baía são expressas em mil frutos e o rendimento médio em frutos/ha.
A8: 7 - Valores para a categoria Total indisponíveis para as variáveis Quantidade produzida e Rendimento médio, pois as unidades de medida diferem para determinados produtos.
A9: 8 - Subentende a possibilidade de cultivos sucessivos ou simultâneos (simples, associados e/ou intercalados) no mesmo ano e no mesmo local, podendo, por isto, a área informada da cultura exceder a área geográfica do município.
A10: 9 - As culturas de abacaxi, cana-de-açúcar, mamona e mandioca são consideradas culturas temporárias de longa duração. Elas costumam ter ciclo vegetativo que ultrapassa 12 meses e, por isso, as informações são computadas nas colheitas realizadas dentro de cada ano civil (12 meses). Nestas culturas a área plantada refere-se a área destinada à colheita no ano.
A11: 10 - A diferença entre a área plantada ou destinada à colheita e a área colhida na lavoura é considerada como área perdida.
A12: 11 - A variável Área plantada ou destinada à colheita só passou a ser informada a partir de 1988. 12 - Valor da produção: Variável derivada calculada pela média ponderada das informações de quantidade e preço médio corrente pago ao produtor, de acordo com os períodos de colheita e comercialização de cada produto. As despesas de frete, taxas e impostos não são incluídas no preço. 13 - Os dados do último ano divulgado são RESULTADOS PRELIMINARES e podem sofrer alterações até a próxima divulgação.
A14: Legenda
A15: Símbolo | B15: Significado
A16: - | B16: Zero absoluto, não resultante de um cálculo ou arredondamento. Ex: Em determinado município não existem pessoas de 14 anos de idade sem instrução.
A17: 0 | B17: Zero resultante de um cálculo ou arredondamento. Ex: A inflação do feijão em determinada Região Metropolitana foi 0. Determinado município produziu 400 kg de sementes de girassol e os dados da tabela são expressos em toneladas.
A18: X | B18: Valor inibido para não identificar o informante. Ex: Determinado município só possui uma empresa produtora de cimento, logo o valor de sua produção deve ser inibido.
A19: .. | B19: Valor não se aplica. Ex: Não se pode obter o total da produção agrícola em determinado município quando os produtos agrícolas são contabilizados com unidades de medida distintas.
A20: ... | B20: Valor não disponível. Ex: A produção de feijão em determinado município não foi pesquisada ou determinado município não existia no ano da pesquisa.
A21: A a Z (exceto X) | B21: Significa uma faixa de valores. Varia em função da tabela (se for o caso). Ex: O nível de precisão da produção estimada de combustíveis está na faixa A (95 a 100%)
